LICENSE
MANIFEST.in
NOTICE
README.rst
setup.py
pylend/__init__.py
pylend/account.py
pylend/connection.py
pylend/exceptions.py
pylend/loans.py
pylend.egg-info/PKG-INFO
pylend.egg-info/SOURCES.txt
pylend.egg-info/dependency_links.txt
pylend.egg-info/not-zip-safe
pylend.egg-info/requires.txt
pylend.egg-info/top_level.txt